{"transcript":"Ōá…ôňąs…ônt…¶…ôit","exists":true,"definitions":["Die innerlike houding of ingesteldheid van 'n persoon teenoor iets of iemand.","Die morele of geestelike ingesteldheid van 'n individu."],"examples":["Sy het 'n positiewe gesindheid.","Hulle toon 'n goeie gesindheid teenoor mekaar.","Verander jou gesindheid."],"lemma":"gesindheid","lemmaPos":"noun","synonyms":["houding","ingesteldheid","mentaliteit","gesindte"],"number":"singular","pluralForm":"die gesindhede","source":"gesindheid"}